uhomepy/__init__.py
uhomepy-0.9.0.dist-info/LICENSE
uhomepy-0.9.0.dist-info/METADATA
uhomepy-0.9.0.dist-info/WHEEL
uhomepy-0.9.0.dist-info/top_level.txt
uhomepy-0.9.0.dist-info/RECORD
