Metadata-Version: 2.2
Name: uhomepy
Version: 0.9.0
Summary: A python interface for the Uhome OpenAPI
Author-email: Jan Karachale <jellojank@gmail.com>
License: MIT
Project-URL: homepage, https://github.com/jellojank/uhomepy
Project-URL: issues, https://github.com/jellojank/uhomepy/issues
Classifier: Intended Audience :: Developers
Classifier: Operating System :: OS Independent
Classifier: Programming Language :: Python :: 3
Requires-Python: >=3.11
License-File: LICENSE
Requires-Dist: aiohttp
